entities.py
pelican_entities-1.0.0.dist-info/LICENSE
pelican_entities-1.0.0.dist-info/METADATA
pelican_entities-1.0.0.dist-info/WHEEL
pelican_entities-1.0.0.dist-info/top_level.txt
pelican_entities-1.0.0.dist-info/RECORD
