Metadata-Version: 2.1
Name: pelican-entities
Version: 1.0.0
Summary: A generator for Pelican, allowing the use of generic entities in place of the default page and article ones
Home-page: https://github.com/AlexJF/pelican-entities
Download-URL: https://github.com/AlexJF/pelican-entities/archive/v1.0.0.zip
Author: Alexandre Fonseca
Author-email: alexandrejorgefonseca@gmail.com
License: Apache
Keywords: pelican blog static generic entities
Platform: UNKNOWN
License-File: LICENSE
Requires-Dist: pelican (<5,>=4)
